{
    "subjects": [{
        "questions": [{
            "answers": [{
                "answer": "10",
                "isCorrect": true
            }, {
                "answer": "73",
                "isCorrect": false
            }, {
                "answer": "9",
                "isCorrect": false
            }, {
                "answer": "17",
                "isCorrect": false
            }],
            "question": "What is 7 + 3?"
        }, {
            "answers": [{
                "answer": "14",
                "isCorrect": false
            }, {
                "answer": "16",
                "isCorrect": false
            }, {
                "answer": "20",
                "isCorrect": false
            }, {
                "answer": "15",
                "isCorrect": true
            }],
            "question": "What is 23 - 8?"
        }, {
            "answers": [{
                "answer": "63",
                "isCorrect": false
            }, {
                "answer": "98",
                "isCorrect": false
            }, {
                "answer": "72",
                "isCorrect": true
            }, {
                "answer": "81",
                "isCorrect": false
            }],
            "question": "What is 9 * 8?"
        }, {
            "answers": [{
                "answer": "13",
                "isCorrect": false
            }, {
                "answer": "12",
                "isCorrect": true
            }, {
                "answer": "10",
                "isCorrect": false
            }, {
                "answer": "11",
                "isCorrect": false
            }],
            "question": "What is 60 \/ 5?"
        }, {
            "answers": [{
                "answer": "56",
                "isCorrect": true
            }, {
                "answer": "-60",
                "isCorrect": false
            }, {
                "answer": "46",
                "isCorrect": false
            }, {
                "answer": "33",
                "isCorrect": false
            }],
            "question": "What is (30 * 2) - 4?"
        }, {
            "answers": [{
                "answer": "15",
                "isCorrect": false
            }, {
                "answer": "243",
                "isCorrect": true
            }, {
                "answer": "128",
                "isCorrect": false
            }, {
                "answer": "35",
                "isCorrect": false
            }],
            "question": "What is 3^5?"
        }],
        "subjectTitle": "Mathematics",
        "description": "Lots of numbers"
    }, {
        "questions": [{
            "answers": [{
                "answer": "The Flash",
                "isCorrect": false
            }, {
                "answer": "Doctor Strange",
                "isCorrect": true
            }, {
                "answer": "Wolverine",
                "isCorrect": false
            }, {
                "answer": "Thanos",
                "isCorrect": false
            }],
            "question": "Which of these is an Avenger?"
        }, {
            "answers": [{
                "answer": "ShieldMan",
                "isCorrect": false
            }, {
                "answer": "AntMan",
                "isCorrect": false
            }, {
                "answer": "Captain America",
                "isCorrect": true
            }, {
                "answer": "Captain Marvel",
                "isCorrect": false
            }],
            "question": "Which Avenger uses a round shield that acts as a boomerang?"
        }, {
            "answers": [{
                "answer": "Thor",
                "isCorrect": true
            }, {
                "answer": "Iron Man",
                "isCorrect": true
            }, {
                "answer": "Wolverine",
                "isCorrect": false
            }, {
                "answer": "Galactus",
                "isCorrect": false
            }],
            "question": "Which Marvel Hero beheads Thanos (MCU)?"
        }, {
            "answers": [{
                "answer": "Space, Reality, Power, Mind, Time",
                "isCorrect": true
            }, {
                "answer": "Death, Power, Life, Love, Rage",
                "isCorrect": false
            }, {
                "answer": "Power, Courage, Wisdom",
                "isCorrect": false
            }, {
                "answer": "Earth, Wind, Water, Fire",
                "isCorrect": false
            }],
            "question": "Name the Infinity Stones."
        }],
        "subjectTitle": "Marvel Super Heroes",
        "description": "Avengers assemble"
    }, {
        "questions": [{
            "answers": [{
                "answer": "The way the sun's light travels through the atmosphere",
                "isCorrect": true
            }, {
                "answer": "A reflection of all the water on Earth",
                "isCorrect": false
            }, {
                "answer": "The atmosphere contains particles that are blueish in color",
                "isCorrect": false
            }, {
                "answer": "It's not blue, but in fact the way our eyes see space",
                "isCorrect": false
            }],
            "question": "Why is the sky blue?"
        }],
        "subjectTitle": "Science",
        "description": "How the world works"
    }]
}
